binja_mcp.py
binja_mcp-0.1.8.dist-info/METADATA
binja_mcp-0.1.8.dist-info/WHEEL
binja_mcp-0.1.8.dist-info/entry_points.txt
binja_mcp-0.1.8.dist-info/top_level.txt
binja_mcp-0.1.8.dist-info/RECORD
